Metadata-Version: 2.1
Name: retico-chatgpt
Version: 0.0.1
Summary: The chatgpt incremental module for the retico framework
Home-page: https://github.com/retico-team/retico-chatgpt
Download-URL: https://github.com/retico-team/retico-chatgpt
Author: Thilo Michael
Author-email: uhlomuhlo@gmail.com
Keywords: retico,framework,incremental,dialogue,dialog,chat,gpt,openai
Classifier: Development Status :: 2 - Pre-Alpha
Classifier: Programming Language :: Python :: 3
Classifier: License :: OSI Approved :: Apache Software License
Requires-Python: >=3.6, <4
License-File: LICENSE
